pyaltiforce/__init__.py
pyaltiforce/altiforce.py
pyaltiforce/helpers.py
pyaltiforce-1.1.0.dist-info/entry_points.txt
pyaltiforce-1.1.0.dist-info/WHEEL
pyaltiforce-1.1.0.dist-info/METADATA
pyaltiforce-1.1.0.dist-info/RECORD
